transtool/__init__.py
transtool/apps.py
transtool/settings.py
transtool/tools.py
transtool/views.py
transtool/management/__init__.py
transtool/management/commands/__init__.py
transtool/management/commands/transtool_compilemessages.py
transtool/management/commands/transtool_import.py
transtool/management/commands/transtool_makemessages.py
django_transtool-0.0.19.dist-info/LICENSE
django_transtool-0.0.19.dist-info/METADATA
django_transtool-0.0.19.dist-info/WHEEL
django_transtool-0.0.19.dist-info/top_level.txt
django_transtool-0.0.19.dist-info/RECORD
