Metadata-Version: 2.1
Name: django-transtool
Version: 0.0.19
Summary: Make translating your django project easier.
Home-page: https://github.com/liminspace/django-transtool
Author: Igor Melnyk @liminspace
Author-email: liminspace@gmail.com
License: MIT
Keywords: django,django-transtool,translation,localization,internationalization,i18n,l10n
Platform: UNKNOWN
Classifier: Programming Language :: Python
Classifier: Programming Language :: Python :: 2
Classifier: Programming Language :: Python :: 2.7
Classifier: Programming Language :: Python :: 3
Classifier: Programming Language :: Python :: 3.5
Classifier: Programming Language :: Python :: 3.6
Classifier: Intended Audience :: Developers
Classifier: Topic :: Software Development :: Libraries
Classifier: Topic :: Software Development :: Libraries :: Application Frameworks
Classifier: Framework :: Django
Classifier: License :: OSI Approved :: MIT License
Requires-Dist: django (<2.3,>=1.8)
Requires-Dist: requests (>=2.15.1)
Requires-Dist: polib (>=1.1.0)
